cowechatapi/__init__.py
cowechatapi/cowechat.py
cowechatapi/cowechat_api.py
cowechatapi-0.1.5.dist-info/LICENSES.txt
cowechatapi-0.1.5.dist-info/METADATA
cowechatapi-0.1.5.dist-info/WHEEL
cowechatapi-0.1.5.dist-info/entry_points.txt
cowechatapi-0.1.5.dist-info/top_level.txt
cowechatapi-0.1.5.dist-info/RECORD
