Metadata-Version: 2.1
Name: cowechatapi
Version: 0.1.5
Summary: A tools for send message to company wechat.
Home-page: https://github.com/nikozhangwj/CoropWechatSendMsgAPI
Author: Niko Zhang
Author-email: 334743423@qq.com
License: UNKNOWN
Keywords: wechat cowechat
Platform: UNKNOWN
Classifier: Programming Language :: Python :: 3
Classifier: License :: OSI Approved :: MIT License
Classifier: Operating System :: OS Independent
Requires-Python: >=3.6
